{
  "slug": "mercato-reviews",
  "namespace": "Mercato\\Reviews",
  "version": "0.1.0",
  "sdk_version": "^0.1",
  "requires": [
    "mercato-core@^0.1",
    "mercato-vendors@^0.1"
  ],
  "provides_events": [
    "mercato.review.created.v1"
  ],
  "consumes_events": [],
  "capabilities": [
    "mercato_reviews_read",
    "mercato_reviews_write",
    "mercato_reviews_admin"
  ],
  "tables": [
    "wp_mercato_reviews"
  ],
  "tier": "domain",
  "feature_flag": "mercato.reviews",
  "phase": "P2"
}
